mficlient/__init__.py
mficlient/client.py
mficlient/fake.py
mficlient/fake_data.py
mficlient/main.py
mficlient-0.4.1.dist-info/METADATA
mficlient-0.4.1.dist-info/WHEEL
mficlient-0.4.1.dist-info/entry_points.txt
mficlient-0.4.1.dist-info/RECORD
