Metadata-Version: 2.1
Name: mficlient
Version: 0.4.1
Summary: A remote control client for Ubiquiti's UVC NVR
Home-page: https://github.com/uilibs/mficlient
Author: Dan Smith
Author-email: dsmith+mficlient@danplanet.com
Requires-Python: >=3.10
Classifier: Development Status :: 5 - Production/Stable
Classifier: Intended Audience :: Developers
Classifier: Natural Language :: English
Classifier: Operating System :: OS Independent
Classifier: Programming Language :: Python :: 3
Classifier: Programming Language :: Python :: 3.10
Classifier: Programming Language :: Python :: 3.11
Classifier: Programming Language :: Python :: 3.12
Classifier: Topic :: Software Development :: Build Tools
Classifier: Topic :: Software Development :: Libraries
Requires-Dist: requests (>=2.26.0,<3.0.0)
Project-URL: Bug Tracker, https://github.com/uilibs/mficlient/issues
Project-URL: Changelog, https://github.com/uilibs/mficlient/blob/main/CHANGELOG.md
Project-URL: Repository, https://github.com/uilibs/mficlient
